README.md
setup.py
memorpy/__init__.py
memorpy/address.py
memorpy/base_process.py
memorpy/linux_process.py
memorpy/linux_structures.py
memorpy/locator.py
memorpy/mem_worker.py
memorpy/osx_process.py
memorpy/process.py
memorpy/structures.py
memorpy/sun_process.py
memorpy/utils.py
memorpy/version.py
memorpy/win_process.py
memorpy/win_structures.py
mempy3.egg-info/PKG-INFO
mempy3.egg-info/SOURCES.txt
mempy3.egg-info/dependency_links.txt
mempy3.egg-info/top_level.txt