Metadata-Version: 2.1
Name: mempy3
Version: 0.0.2
Summary: A python 3 port of memorpy, a library by n1nj4sec
Home-page: https://github.com/starwort/memorpy3
Author: starwort
License: MPL-2.0
Platform: UNKNOWN
Classifier: Programming Language :: Python :: 3.6
